melodically/__init__.py
melodically/chords.py
melodically/harmonic_state.py
melodically/harmony.py
melodically/midi_note_queue.py
melodically/parsers.py
melodically/rhythm.py
melodically-0.0.13.dist-info/LICENSE
melodically-0.0.13.dist-info/METADATA
melodically-0.0.13.dist-info/WHEEL
melodically-0.0.13.dist-info/top_level.txt
melodically-0.0.13.dist-info/RECORD
