Metadata-Version: 2.1
Name: melodically
Version: 0.0.13
Summary: A python module that contains various tools to handle melodic representation and parsing.
Home-page: https://github.com/FedericoDiMarzo/melodically
Author: Federico Di Marzo
Author-email: mail.federicodimarzo@gmail.com
License: UNKNOWN
Project-URL: Bug Tracker, https://github.com/FedericoDiMarzo/melodically/issues
Platform: UNKNOWN
Classifier: Programming Language :: Python :: 3
Classifier: License :: OSI Approved :: MIT License
Classifier: Operating System :: OS Independent
Requires-Python: >=3.6
License-File: LICENSE
